MANIFEST.in
README.md
setup.cfg
setup.py
almar/__init__.py
almar/alma.py
almar/almar.py
almar/authorities.py
almar/bib.py
almar/concept.py
almar/job.py
almar/marc.py
almar/query.py
almar/sru.py
almar/task.py
almar/util.py
almar.egg-info/PKG-INFO
almar.egg-info/SOURCES.txt
almar.egg-info/dependency_links.txt
almar.egg-info/entry_points.txt
almar.egg-info/requires.txt
almar.egg-info/top_level.txt