Metadata-Version: 2.1
Name: almar
Version: 0.8.0
Summary: Search and replace for subject fields in Alma records.
Home-page: https://github.com/scriptotek/almar
Author: Dan Michael O. Heggø
Author-email: d.m.heggo@ub.uio.no
License: MIT
Keywords: marc alma
Platform: UNKNOWN
Classifier: Programming Language :: Python
Classifier: Programming Language :: Python :: 3.5
Classifier: Programming Language :: Python :: 3.6
Classifier: Programming Language :: Python :: 3.7
